{
  "family": "EDC17_GEN",
  "totalPairs": 1701,
  "maps": [
    {
      "sigHex": "0e000a00c800900158022003",
      "sigBytes": [
        14,
        0,
        10,
        0,
        200,
        0,
        144,
        1,
        88,
        2,
        32,
        3
      ],
      "rows": 10,
      "cols": 14,
      "xAxis": [
        200,
        400,
        600,
        800,
        1000,
        1200,
        1600,
        2000,
        4000,
        6000,
        8000,
        9600,
        10300,
        11000
      ],
      "yAxis": [
        0,
        100,
        200,
        300,
        500,
        2500,
        5500,
        6500,
        7500,
        8500
      ],
      "le": true,
      "occurrences": 303,
      "occurrencePct": 17.813051146384478,
      "avgPctChange": 2.1951913806233545,
      "medianPctChange": 2.086655456762232,
      "sampleFiles": [
        "Audi_A3_2.0_TDI_CR_2007_Turbo-Diesel___103KWKW_Bosch__03L906022BQ_396412_053B.Original",
        "Audi_A3_2.0_TDI_CR_2007_Turbo-Diesel___103KWKW_Bosch__03L906022BQ_396412_053B.Original",
        "Audi_A3_2.0_TDI_CR_2007_Turbodiesel___103KWKW_Bosch__03L906022BQ_396412_053B.Original"
      ]
    },
    {
      "sigHex": "10000a0040066009b80bac0d",
      "sigBytes": [
        16,
        0,
        10,
        0,
        64,
        6,
        96,
        9,
        184,
        11,
        172,
        13
      ],
      "rows": 10,
      "cols": 16,
      "xAxis": [
        1600,
        2400,
        3000,
        3500,
        4000,
        4500,
        5000,
        5500,
        6000,
        6500,
        7000,
        7500,
        8000,
        8500,
        9000,
        10800
      ],
      "yAxis": [
        500,
        550,
        600,
        650,
        700,
        750,
        800,
        850,
        925,
        960
      ],
      "le": true,
      "occurrences": 236,
      "occurrencePct": 13.874191651969431,
      "avgPctChange": 6.085136996567358,
      "medianPctChange": 5.984431698466586,
      "sampleFiles": [
        "Audi_A4_2.0_TDI_CR_2017_Turbo-Diesel__100KWKW_Bosch__03L906018DN_515572_7FB4.Original",
        "Audi_Q5_2.0_TDI_CR_2017_Turbo-Diesel__105.2KWKW_Bosch_0281017328_03L906018DN_517530_8A4C.Original",
        "Audi_Q5_2.0_TDI_CR_2017_Turbo-Diesel__105.2KWKW_Bosch__03L906018DN_515568_C454.Original"
      ]
    },
    {
      "sigHex": "0e00080000002003b0044006",
      "sigBytes": [
        14,
        0,
        8,
        0,
        0,
        0,
        32,
        3,
        176,
        4,
        64,
        6
      ],
      "rows": 8,
      "cols": 14,
      "xAxis": [
        0,
        800,
        1200,
        1600,
        1800,
        2000,
        2500,
        3000,
        4000,
        5000,
        6000,
        8000,
        10000,
        11000
      ],
      "yAxis": [
        82,
        328,
        819,
        1884,
        3686,
        5325,
        6963,
        8192
      ],
      "le": true,
      "occurrences": 124,
      "occurrencePct": 7.2898295120517345,
      "avgPctChange": 16.04233068844495,
      "medianPctChange": 19.99291932570193,
      "sampleFiles": [
        "Audi_A4_2.0_TDI_CR__Turbo-Diesel___103KWKW_Bosch__03L906018LD_522896_443E.Original",
        "Audi_A4_2.0_TDI_CR__Turbo-Diesel___103KWKW_Bosch__03L906018LD_522896_443E.Original",
        "Audi_A4_2.0_TDI_CR__Turbo-Diesel___103KWKW_Bosch__03L906018LD_522896_443E.Original"
      ]
    },
    {
      "sigHex": "10000a000000a406d007c409",
      "sigBytes": [
        16,
        0,
        10,
        0,
        0,
        0,
        164,
        6,
        208,
        7,
        196,
        9
      ],
      "rows": 10,
      "cols": 16,
      "xAxis": [
        0,
        1700,
        2000,
        2500,
        3000,
        3500,
        4000,
        4500,
        5000,
        6000,
        7000,
        7500,
        8000,
        8400,
        9000,
        10800
      ],
      "yAxis": [
        500,
        600,
        650,
        700,
        750,
        800,
        850,
        900,
        950,
        975
      ],
      "le": true,
      "occurrences": 94,
      "occurrencePct": 5.526161081716637,
      "avgPctChange": 6.41952154619475,
      "medianPctChange": 4.960140225506882,
      "sampleFiles": [
        "Audi_A4_2.0_TDI_CR_2017_Turbo-Diesel__119.9KWKW_Bosch__03L906018JL_519317_8E68.Original",
        "Audi_A4_2.0_TDI_CR_2017_Turbo-Diesel__125KWKW_Bosch__03L906019AL_515516_DDC3.Original",
        "Audi_A4_2.0_TDI_CR_2017_Turbo-Diesel__130.2KWKW_Bosch__03L906018JL_1037524103_4F78.Original"
      ]
    },
    {
      "sigHex": "10000a004006d0076009280a",
      "sigBytes": [
        16,
        0,
        10,
        0,
        64,
        6,
        208,
        7,
        96,
        9,
        40,
        10
      ],
      "rows": 10,
      "cols": 16,
      "xAxis": [
        1600,
        2000,
        2400,
        2600,
        2800,
        3000,
        3500,
        4000,
        5000,
        6000,
        7000,
        8000,
        8500,
        9000,
        9500,
        10000
      ],
      "yAxis": [
        400,
        500,
        600,
        700,
        750,
        800,
        850,
        900,
        980,
        1000
      ],
      "le": true,
      "occurrences": 84,
      "occurrencePct": 4.938271604938271,
      "avgPctChange": 5.189110655451172,
      "medianPctChange": 4.915839928659005,
      "sampleFiles": [
        "VW_Amarok_2.0_TDI_CR_2017_Turbo-Diesel__89.7KWKW_Bosch__03L906019FB_526356_6ADC.Original",
        "VW_Caddy_2.0_TDI_CR_2017_Turbo-Diesel__132.4KWKW_Bosch__03L906022JB_518077_B43F.Original",
        "VW_Transporter_2.0_TDI_CR_2017_Turbo-Diesel__97.1KWKW_Bosch__03L906019GM_524689_C6C7.Original"
      ]
    },
    {
      "sigHex": "10000a00b004d007c409b80b",
      "sigBytes": [
        16,
        0,
        10,
        0,
        176,
        4,
        208,
        7,
        196,
        9,
        184,
        11
      ],
      "rows": 10,
      "cols": 16,
      "xAxis": [
        1200,
        2000,
        2500,
        3000,
        3500,
        4000,
        4500,
        5000,
        5500,
        6000,
        7000,
        8000,
        8400,
        9000,
        9600,
        10800
      ],
      "yAxis": [
        600,
        650,
        700,
        750,
        800,
        850,
        900,
        930,
        940,
        950
      ],
      "le": true,
      "occurrences": 80,
      "occurrencePct": 4.703115814226925,
      "avgPctChange": 9.06350789457655,
      "medianPctChange": 7.982939076774165,
      "sampleFiles": [
        "Audi_Q3_2.0_TDI_CR__2017_Turbo-Diesel___103KWKW_Bosch_03L906018CM_03L906018ES_521662_96CA.Original",
        "Audi_Q3_2.0_TDI_CR__2017_Turbo-Diesel___103KWKW_Bosch_03L906018CM_03L906018ES_527083_AC4D.Original",
        "VW_Passat_2.0_TDI_CR_2017_Turbo-Diesel___105.2KWKW_Bosch__03L906018PR_526304_1D44.Original"
      ]
    },
    {
      "sigHex": "03000a000000e8034c040000",
      "sigBytes": [
        3,
        0,
        10,
        0,
        0,
        0,
        232,
        3,
        76,
        4,
        0,
        0
      ],
      "rows": 10,
      "cols": 3,
      "xAxis": [
        0,
        1000,
        1100
      ],
      "yAxis": [
        0,
        1000,
        2000,
        3000,
        4000,
        5000,
        5500,
        6000,
        6500,
        8000
      ],
      "le": true,
      "occurrences": 41,
      "occurrencePct": 2.410346854791299,
      "avgPctChange": 9.490022172949004,
      "medianPctChange": 8.000000000000007,
      "sampleFiles": [
        "VW_Transporter_2.0_TDI_CR___2017_Turbo-Diesel__132.4KWKW_Bosch__508906P755W_508906_3D0B.Original",
        "VW_Transporter_2.0_TDI_CR___2017_Turbo-Diesel__132.4KWKW_Bosch__508906P755W_508906_3D0B.Original",
        "VW_Amarok_2.0_TDI_CR_2001_Turbo-Diesel___119.9KWKW_Bosch__03L906022SP_510909_78A6.Original"
      ]
    },
    {
      "sigHex": "06001500f4015802bc022003",
      "sigBytes": [
        6,
        0,
        21,
        0,
        244,
        1,
        88,
        2,
        188,
        2,
        32,
        3
      ],
      "rows": 21,
      "cols": 6,
      "xAxis": [
        500,
        600,
        700,
        800,
        900,
        950
      ],
      "yAxis": [
        1600,
        2000,
        2500,
        2800,
        3000,
        3500,
        4000,
        4500,
        5000,
        5500,
        6000,
        6500,
        7000,
        7500,
        8000,
        8500,
        8800,
        9000,
        9500,
        10000,
        11000
      ],
      "le": true,
      "occurrences": 39,
      "occurrencePct": 2.2927689594356258,
      "avgPctChange": 21.725991244224986,
      "medianPctChange": 21.271376482272398,
      "sampleFiles": [
        "Audi_A4_3.0_TDI_CR_2017_Turbo-Diesel__180.2KWKW_Bosch__4G0907401___528339_58D4.Original",
        "Audi_A4_3.0_TDI_CR_2017_Turbo-Diesel__180.2KWKW_Bosch__4G0907401___528339_58D4.Original",
        "Audi_A4_3.0_TDI_CR_2017_Turbo-Diesel__180.2KWKW_Bosch__4G0907401___528339_58D4.Original"
      ]
    },
    {
      "sigHex": "1000080000002003b0047805",
      "sigBytes": [
        16,
        0,
        8,
        0,
        0,
        0,
        32,
        3,
        176,
        4,
        120,
        5
      ],
      "rows": 8,
      "cols": 16,
      "xAxis": [
        0,
        800,
        1200,
        1400,
        1600,
        1800,
        2000,
        2200,
        2400,
        3000,
        4000,
        5000,
        6000,
        8000,
        10000,
        10710
      ],
      "yAxis": [
        82,
        328,
        819,
        1638,
        3277,
        4915,
        6554,
        8192
      ],
      "le": true,
      "occurrences": 39,
      "occurrencePct": 2.2927689594356258,
      "avgPctChange": 16.53686641079992,
      "medianPctChange": 19.999999999999996,
      "sampleFiles": [
        "Audi_A4_2.0_TDI_CR__Turbo-Diesel___103KWKW_Bosch__03L906018LD_522896_443E.Original",
        "Audi_Q5_2.0_TDI_CR_2010_Turbo-Diesel___103KWKW_Bosch__03L906018DN_515568_C454.Original",
        "Audi_Q5_2.0_TDI_CR_2010_Turbo-Diesel___103KWKW_Bosch__03L906018DN_515568_C454.Original"
      ]
    },
    {
      "sigHex": "0e0008000000b0044006d007",
      "sigBytes": [
        14,
        0,
        8,
        0,
        0,
        0,
        176,
        4,
        64,
        6,
        208,
        7
      ],
      "rows": 8,
      "cols": 14,
      "xAxis": [
        0,
        1200,
        1600,
        2000,
        2400,
        2800,
        3200,
        4000,
        5000,
        6000,
        7000,
        8000,
        10000,
        11000
      ],
      "yAxis": [
        82,
        410,
        819,
        1638,
        2458,
        4096,
        5734,
        7373
      ],
      "le": true,
      "occurrences": 39,
      "occurrencePct": 2.2927689594356258,
      "avgPctChange": 3.867254984149578,
      "medianPctChange": 3.9133718295786046,
      "sampleFiles": [
        "VW_Amarok_2.0_TDI_CR_2010_Turbodiesel___88.3KWKW_Bosch__03L906022CD_518131_B798.Original",
        "VW_Amarok_2.0_TDI_CR_2010_Turbodiesel___88.3KWKW_Bosch__03L906022CD_518131_B798.Original",
        "VW_Amarok_2.0_TDI_CR_2010_Turbodiesel___88.3KWKW_Bosch__03L906022CD_518131_B798.Original"
      ]
    },
    {
      "sigHex": "0a000700780540060807d007",
      "sigBytes": [
        10,
        0,
        7,
        0,
        120,
        5,
        64,
        6,
        8,
        7,
        208,
        7
      ],
      "rows": 7,
      "cols": 10,
      "xAxis": [
        1400,
        1600,
        1800,
        2000,
        2400,
        2800,
        3200,
        3600,
        4000,
        6000
      ],
      "yAxis": [
        2481,
        2581,
        2681,
        2781,
        2831,
        2931,
        3031
      ],
      "le": true,
      "occurrences": 38,
      "occurrencePct": 2.2339800117577897,
      "avgPctChange": 19.848230115671484,
      "medianPctChange": 30.69400630914827,
      "sampleFiles": [
        "VW_California_2.0_TDI_CR_2017_Turbo-Diesel__103KWKW_Bosch__03L906022GH_518142_ED4D.Original",
        "VW_California_2.0_TDI_CR_2017_Turbo-Diesel__103KWKW_Bosch__03L906022GH_518142_ED4D.Original",
        "VW_California_2.0_TDI_CR_2012_Turbo-Diesel__103KWKW_Bosch__03L906022GH_518142_ED4D.Original"
      ]
    },
    {
      "sigHex": "1000080040066009b80bac0d",
      "sigBytes": [
        16,
        0,
        8,
        0,
        64,
        6,
        96,
        9,
        184,
        11,
        172,
        13
      ],
      "rows": 8,
      "cols": 16,
      "xAxis": [
        1600,
        2400,
        3000,
        3500,
        4000,
        4500,
        5000,
        5600,
        6000,
        6500,
        7000,
        7500,
        8000,
        9000,
        10000,
        11000
      ],
      "yAxis": [
        400,
        500,
        600,
        700,
        800,
        900,
        950,
        1000
      ],
      "le": true,
      "occurrences": 37,
      "occurrencePct": 2.175191064079953,
      "avgPctChange": 7.857626389198925,
      "medianPctChange": 8.764602577632541,
      "sampleFiles": [
        "VW_Amarok_2.0_BiTDI_CR_2017_Turbo-Diesel___119.9KWKW_Bosch_03L907309K_03L906019FA_526355_7B99.Original",
        "VW_Amarok_2.0_TDI_CR_2017_Turbo-Diesel__119.9KWKW_Bosch__03L906019FA_518108_07B1.Original",
        "VW_Amarok_2.0_BiTDI_CR_2017_Turbo-Diesel___119.9KWKW_Bosch_03L907309K_03L906019FA_526355_7B99.Original"
      ]
    },
    {
      "sigHex": "100008007805d007c409b80b",
      "sigBytes": [
        16,
        0,
        8,
        0,
        120,
        5,
        208,
        7,
        196,
        9,
        184,
        11
      ],
      "rows": 8,
      "cols": 16,
      "xAxis": [
        1400,
        2000,
        2500,
        3000,
        3500,
        4000,
        5000,
        6000,
        7000,
        7500,
        8000,
        8500,
        9000,
        9500,
        10000,
        10500
      ],
      "yAxis": [
        500,
        600,
        700,
        750,
        800,
        850,
        900,
        950
      ],
      "le": true,
      "occurrences": 29,
      "occurrencePct": 1.7048794826572604,
      "avgPctChange": 9.808965918541602,
      "medianPctChange": 9.61566096378319,
      "sampleFiles": [
        "Audi_A4_3.0_TDI_CR_2017_Turbo-Diesel__180.2KWKW_Bosch__4G0907401___528339_58D4.Original",
        "Audi_A5_3.0_TDI_CR_2017_Turbo-Diesel__180.2KWKW_Bosch__4G0907401___528339_58D4.Original",
        "Audi_A5_3.0_TDI_CR_2017_Turbo-Diesel__180.2KWKW_Bosch__4G0907401___528339_58D4.Original"
      ]
    },
    {
      "sigHex": "080008000000e803d007b80b",
      "sigBytes": [
        8,
        0,
        8,
        0,
        0,
        0,
        232,
        3,
        208,
        7,
        184,
        11
      ],
      "rows": 8,
      "cols": 8,
      "xAxis": [
        0,
        1000,
        2000,
        3000,
        4000,
        5000,
        6000,
        9000
      ],
      "yAxis": [
        2931,
        3131,
        3331,
        3531,
        3731,
        3831,
        3931,
        4221
      ],
      "le": true,
      "occurrences": 29,
      "occurrencePct": 1.7048794826572604,
      "avgPctChange": 4.684901819923375,
      "medianPctChange": 2.750000000000008,
      "sampleFiles": [
        "Audi_A4_2.0_TDI_CR_2008_Turbo-Diesel__100KWKW_Bosch__03L906022B__396483_BCFD.Original",
        "Audi_A4_2.0_TDI_CR_2008_Turbo-Diesel___105.2KWKW_Bosch_03L906022JP_03L906022B__396469_090A.Original",
        "Audi_A4_2.0_TDI_CR_2008_Turbo-Diesel___88.3KWKW_Bosch__03L906022B__396468_02E6.Original"
      ]
    },
    {
      "sigHex": "06000400a00f301188135014",
      "sigBytes": [
        6,
        0,
        4,
        0,
        160,
        15,
        48,
        17,
        136,
        19,
        80,
        20
      ],
      "rows": 4,
      "cols": 6,
      "xAxis": [
        4000,
        4400,
        5000,
        5200,
        7400,
        10000
      ],
      "yAxis": [
        0,
        1500,
        3000,
        17000
      ],
      "le": true,
      "occurrences": 28,
      "occurrencePct": 1.646090534979424,
      "avgPctChange": 208.59616573902284,
      "medianPctChange": 233.33333333333334,
      "sampleFiles": [
        "Audi_A4_3.0_TDI_CR_2017_Turbo-Diesel__180.2KWKW_Bosch__4G0907401___528339_58D4.Original",
        "Audi_A5_3.0_TDI_CR_2017_Turbo-Diesel__180.2KWKW_Bosch__4G0907401___528339_58D4.Original",
        "Audi_A5_3.0_TDI_CR_2017_Turbo-Diesel__180.2KWKW_Bosch__4G0907401___528339_58D4.Original"
      ]
    },
    {
      "sigHex": "0f0007007805d007c409b80b",
      "sigBytes": [
        15,
        0,
        7,
        0,
        120,
        5,
        208,
        7,
        196,
        9,
        184,
        11
      ],
      "rows": 7,
      "cols": 15,
      "xAxis": [
        1400,
        2000,
        2500,
        3000,
        3500,
        4000,
        5000,
        6000,
        7000,
        7500,
        8000,
        8500,
        9000,
        9500,
        10000
      ],
      "yAxis": [
        500,
        700,
        750,
        800,
        850,
        900,
        950
      ],
      "le": true,
      "occurrences": 27,
      "occurrencePct": 1.5873015873015872,
      "avgPctChange": 11.414445089330993,
      "medianPctChange": 10.932546190007653,
      "sampleFiles": [
        "Audi_A4_3.0_TDI_CR_2017_Turbo-Diesel__180.2KWKW_Bosch__4G0907401___528339_58D4.Original",
        "Audi_A5_3.0_TDI_CR_2017_Turbo-Diesel__180.2KWKW_Bosch__4G0907401___528339_58D4.Original",
        "Audi_A5_3.0_TDI_CR_2017_Turbo-Diesel__180.2KWKW_Bosch__4G0907401___528339_58D4.Original"
      ]
    },
    {
      "sigHex": "100008000000ca0294055e08",
      "sigBytes": [
        16,
        0,
        8,
        0,
        0,
        0,
        202,
        2,
        148,
        5,
        94,
        8
      ],
      "rows": 8,
      "cols": 16,
      "xAxis": [
        0,
        714,
        1428,
        2142,
        2856,
        3570,
        4284,
        4998,
        5712,
        6426,
        7140,
        7854,
        8568,
        9282,
        9996,
        10710
      ],
      "yAxis": [
        82,
        1241,
        2399,
        3558,
        4716,
        5875,
        7033,
        8192
      ],
      "le": true,
      "occurrences": 25,
      "occurrencePct": 1.4697236919459142,
      "avgPctChange": 16.583161100837593,
      "medianPctChange": 19.980652981305646,
      "sampleFiles": [
        "Audi_A4_2.0_TDI_CR__Turbo-Diesel___103KWKW_Bosch__03L906018LD_522896_443E.Original",
        "VW_Golf_2.0_TDI_CR_2010_Turbo-Diesel___125KWKW_Bosch__03L906018BB_525556_A535.Original",
        "VW_Passat_2.0_TDI_CR_2011_Turbo-Diesel___125KWKW_Bosch__03L906018BE_510958_AB19.Original"
      ]
    },
    {
      "sigHex": "0c0004000a0190012003b004",
      "sigBytes": [
        12,
        0,
        4,
        0,
        10,
        1,
        144,
        1,
        32,
        3,
        176,
        4
      ],
      "rows": 4,
      "cols": 12,
      "xAxis": [
        266,
        400,
        800,
        1200,
        1600,
        2000,
        2666,
        3000,
        3500,
        8000,
        10000,
        11000
      ],
      "yAxis": [
        0,
        2000,
        4000,
        6000
      ],
      "le": true,
      "occurrences": 24,
      "occurrencePct": 1.4109347442680775,
      "avgPctChange": 2.9354959508724776,
      "medianPctChange": 1.9980266403551994,
      "sampleFiles": [
        "Audi_A4_3.0_TDI_CR_2017_Turbo-Diesel__180.2KWKW_Bosch__4G0907401___528339_58D4.Original",
        "Audi_A5_3.0_TDI_CR_2017_Turbo-Diesel__180.2KWKW_Bosch__4G0907401___528339_58D4.Original",
        "Audi_A5_3.0_TDI_CR_2017_Turbo-Diesel__180.2KWKW_Bosch__4G0907401___528339_58D4.Original"
      ]
    },
    {
      "sigHex": "04000a00f401bc02bd02be02",
      "sigBytes": [
        4,
        0,
        10,
        0,
        244,
        1,
        188,
        2,
        189,
        2,
        190,
        2
      ],
      "rows": 10,
      "cols": 4,
      "xAxis": [
        500,
        700,
        701,
        702
      ],
      "yAxis": [
        400,
        800,
        801,
        802,
        803,
        804,
        805,
        806,
        807,
        808
      ],
      "le": true,
      "occurrences": 21,
      "occurrencePct": 1.2345679012345678,
      "avgPctChange": 50,
      "medianPctChange": 50,
      "sampleFiles": [
        "Audi_A4_2.0_TDI_CR_2008_Turbo-Diesel__100KWKW_Bosch__03L906022B__396483_BCFD.Original",
        "Audi_A4_2.0_TDI_CR_2008_Turbo-Diesel___105.2KWKW_Bosch_03L906022JP_03L906022B__396469_090A.Original",
        "Audi_A4_2.0_TDI_CR_2008_Turbo-Diesel___88.3KWKW_Bosch__03L906022B__396468_02E6.Original"
      ]
    },
    {
      "sigHex": "100008000000b0044006d007",
      "sigBytes": [
        16,
        0,
        8,
        0,
        0,
        0,
        176,
        4,
        64,
        6,
        208,
        7
      ],
      "rows": 8,
      "cols": 16,
      "xAxis": [
        0,
        1200,
        1600,
        2000,
        2400,
        3000,
        3500,
        4000,
        4500,
        5000,
        6000,
        7000,
        8000,
        9500,
        10000,
        11000
      ],
      "yAxis": [
        82,
        328,
        819,
        1638,
        2458,
        4096,
        5734,
        7373
      ],
      "le": true,
      "occurrences": 21,
      "occurrencePct": 1.2345679012345678,
      "avgPctChange": 9.738232983818438,
      "medianPctChange": 8.029595460202565,
      "sampleFiles": [
        "VW_Amarok_2.0_TDI_CR_2010_Turbo-Diesel___85KWKW_Bosch__03L906019FE_518171_5608.Original",
        "VW_Amarok_2.0_TDI_CR_2010_Turbo-Diesel___85KWKW_Bosch__03L906019FE_518171_5608.Original",
        "VW_Amarok_2.0_TDI_CR_2010_Turbo-Diesel___85KWKW_Bosch__03L906019FE_518171_5608.Original"
      ]
    },
    {
      "sigHex": "0e000800e803b0044006d007",
      "sigBytes": [
        14,
        0,
        8,
        0,
        232,
        3,
        176,
        4,
        64,
        6,
        208,
        7
      ],
      "rows": 8,
      "cols": 14,
      "xAxis": [
        1000,
        1200,
        1600,
        2000,
        2400,
        2800,
        3200,
        4000,
        5000,
        6000,
        7000,
        8000,
        10000,
        11000
      ],
      "yAxis": [
        82,
        410,
        819,
        1638,
        2458,
        4096,
        5734,
        7373
      ],
      "le": true,
      "occurrences": 21,
      "occurrencePct": 1.2345679012345678,
      "avgPctChange": 15.697949441597224,
      "medianPctChange": 19.985320566334796,
      "sampleFiles": [
        "VW_Amarok_2.0_TDI_CR_2010_Turbodiesel___88.3KWKW_Bosch__03L906022CD_518131_B798.Original",
        "VW_Transporter_2.0_TDI_CR_DPF_2010_Turbo-Diesel___103KWKW_Bosch__03L906022CB_518155_1081.Original",
        "VW_Transporter_2.0_TDI_CR_DPF_2010_Turbo-Diesel___103KWKW_Bosch__03L906022CD_518131_18E9.Original"
      ]
    },
    {
      "sigHex": "04001900900158020c036603",
      "sigBytes": [
        4,
        0,
        25,
        0,
        144,
        1,
        88,
        2,
        12,
        3,
        102,
        3
      ],
      "rows": 25,
      "cols": 4,
      "xAxis": [
        400,
        600,
        780,
        870
      ],
      "yAxis": [
        1000,
        1200,
        1500,
        1800,
        2000,
        2200,
        2500,
        3000,
        3500,
        4000,
        4500,
        5000,
        5500,
        5800,
        6000,
        6500,
        6700,
        7000,
        7500,
        8000,
        8500,
        9000,
        9500,
        9800,
        10000
      ],
      "le": true,
      "occurrences": 20,
      "occurrencePct": 1.1757789535567313,
      "avgPctChange": 30.17034282900975,
      "medianPctChange": 24.054989975785656,
      "sampleFiles": [
        "VW_Transporter_2.0_TDI_CR_2019_Turbo-Diesel__83.8KWKW_Bosch__03L906019FJ_535317_6FD6.Original",
        "VW_Transporter_2.0_TDI_CR_2019_Turbo-Diesel__83.8KWKW_Bosch__03L906019FJ_535317_6FD6.Original",
        "VW_Transporter_2.0_TDI_CR_2014_Turbo-Diesel__83.8KWKW_Bosch__03L906019FJ_535317_6FD6.Original"
      ]
    },
    {
      "sigHex": "100010000000a406d007c409",
      "sigBytes": [
        16,
        0,
        16,
        0,
        0,
        0,
        164,
        6,
        208,
        7,
        196,
        9
      ],
      "rows": 16,
      "cols": 16,
      "xAxis": [
        0,
        1700,
        2000,
        2500,
        3000,
        3500,
        4000,
        4500,
        5000,
        6000,
        7000,
        7500,
        8000,
        8400,
        9000,
        10000
      ],
      "yAxis": [
        500,
        600,
        650,
        700,
        725,
        750,
        775,
        800,
        825,
        850,
        875,
        900,
        925,
        950,
        975,
        990
      ],
      "le": true,
      "occurrences": 18,
      "occurrencePct": 1.0582010582010581,
      "avgPctChange": 7.667207861176339,
      "medianPctChange": 7.854327811483053,
      "sampleFiles": [
        "Audi_Q5_2.0_TDI_CR_2017_Turbo-Diesel__119.9KWKW_Bosch__03L906018DN_521636_D38C.Original",
        "Audi_Q5_2.0_TDI_CR_2017_Turbo-Diesel__125KWKW_Bosch__03L906018DN_521080_E82A.Original",
        "Audi_A4_2.0_TDI_CR__2008_Turbo-Diesel___125KWKW_Bosch_03L906022KC_03L906022B__396477_1E20.Original"
      ]
    },
    {
      "sigHex": "0e00080000000f0014001900",
      "sigBytes": [
        14,
        0,
        8,
        0,
        0,
        0,
        15,
        0,
        20,
        0,
        25,
        0
      ],
      "rows": 8,
      "cols": 14,
      "xAxis": [
        0,
        15,
        20,
        25,
        30,
        35,
        40,
        50,
        63,
        75,
        88,
        100,
        125,
        138
      ],
      "yAxis": [
        2,
        12,
        25,
        51,
        76,
        128,
        179,
        230
      ],
      "le": true,
      "occurrences": 18,
      "occurrencePct": 1.0582010582010581,
      "avgPctChange": 14.98006803569747,
      "medianPctChange": 19.980387632671892,
      "sampleFiles": [
        "VW_Amarok_2.0_TDI_CR_2010_Turbodiesel___88.3KWKW_Bosch__03L906022CD_518131_B798.Original",
        "VW_Transporter_2.0_TDI_CR_DPF_2010_Turbo-Diesel___103KWKW_Bosch__03L906022CB_518155_1081.Original",
        "VW_Transporter_2.0_TDI_CR_DPF_2010_Turbo-Diesel___103KWKW_Bosch__03L906022CD_518131_18E9.Original"
      ]
    }
  ]
}